DataComparerLibrary/__init__.py
DataComparerLibrary/datacomparer.py
DataComparerLibrary/datasorter.py
DataComparerLibrary/datetimehandler.py
DataComparerLibrary/delimitertranslator.py
DataComparerLibrary/field.py
DataComparerLibrary/fileconverter.py
DataComparerLibrary/matchstatus.py
DataComparerLibrary/report.py
DataComparerLibrary/row.py
DataComparerLibrary/tools.py
DataComparerLibrary/twodarray.py
datacomparerlibrary-0.854.dist-info/licenses/LICENSE.txt
datacomparerlibrary-0.854.dist-info/METADATA
datacomparerlibrary-0.854.dist-info/WHEEL
datacomparerlibrary-0.854.dist-info/top_level.txt
datacomparerlibrary-0.854.dist-info/RECORD
