Metadata-Version: 2.4
Name: DataComparerLibrary
Version: 0.854
Summary: For comparing csv-files, 2d-array with a csv-file or 2d-arrays. For comparing text-files, text variable with a text-file or text variables. Including a sorting module.
Author-email: René Philip Zuijderduijn <datacomparerlibrary@outlook.com>
License-Expression: Apache-2.0
Keywords: robotframework,Robot Framework,testing,test-automation,datacompare,data compare,compare csv files,compare text files,compare txt files,compare arrays,compare text
Classifier: Development Status :: 5 - Production/Stable
Classifier: Operating System :: Microsoft :: Windows :: Windows 10
Classifier: Operating System :: Microsoft :: Windows :: Windows 11
Classifier: Programming Language :: Python :: 3.8
Classifier: Programming Language :: Python :: 3.9
Classifier: Programming Language :: Python :: 3.10
Classifier: Programming Language :: Python :: 3.11
Classifier: Programming Language :: Python :: 3.12
Classifier: Programming Language :: Python :: 3.13
Classifier: Topic :: Software Development :: Testing
Requires-Python: >=3.8
License-File: LICENSE.txt
Requires-Dist: python-dateutil
Dynamic: license-file
